svhnl/__init__.py
svhnl/converter.py
svhnl/downloader.py
svhnl-0.0.5.dist-info/LICENSE
svhnl-0.0.5.dist-info/METADATA
svhnl-0.0.5.dist-info/WHEEL
svhnl-0.0.5.dist-info/top_level.txt
svhnl-0.0.5.dist-info/RECORD
